{
  "title": "Buying Near App State: Boone NC Real Estate Guide",
  "slug": "2026-04-29-buying-home-near-app-state-boone-nc-real-estate-guide",
  "date": "April 29, 2026",
  "tag": "relocation",
  "excerpt": "If your student just committed to Appalachian State, you may be wondering whether buying a home in Boone makes more sense than paying four years of rent. Here's what out-of-state families need to know before stepping into the High Country real estate market.",
  "image": "/assets/blog/blue-ridge-mountains-north-carolina.jpg",
  "image_alt": "Downtown Boone NC with mountain views in spring near Appalachian State University"
}